{"__type__":"sp.SkeletonData","_name":"Player_Coin","_native":"raw-skeleton.json","_skeletonJson":{"skeleton":{"hash":"TS2LB4hPL0+h9WiZyCHjC6uOdN4","spine":"3.6.53","width":962,"height":1730,"images":"./images/"},"bones":[{"name":"root"},{"name":"Coin","parent":"root","x":0.86,"y":-14.71,"scaleX":0.789,"scaleY":0.789},{"name":"Coin1","parent":"Coin","x":0.4,"y":8.45},{"name":"Coin2","parent":"Coin","y":14.63},{"name":"Coin3","parent":"Coin","y":14.63}],"slots":[{"name":"Bg","bone":"root"},{"name":"Coin","bone":"Coin3","attachment":"Coin"},{"name":"Coin1","bone":"Coin1","attachment":"Coin1"},{"name":"Coin4","bone":"Coin1","attachment":"Coin1","blend":"additive"},{"name":"Coin2","bone":"Coin2","attachment":"Coin"},{"name":"Coin3","bone":"Coin2","color":"ffffff49","attachment":"Coin","blend":"additive"}],"skins":{"default":{"Coin":{"Coin":{"x":0.14,"y":0.57,"width":42,"height":41}},"Coin1":{"Coin1":{"type":"mesh","uvs":[0,0.8789,0,0.73724,0,0.5948,0,0.47656,0,0.35597,0,0.24331,0,0.12155,0,0,1,0,1,0.11921,1,0.24448,1,0.35597,1,0.47656,1,0.60299,1,0.73841,1,0.87305,1,1,0,1],"triangles":[7,8,9,6,7,9,10,5,6,10,6,9,4,5,10,4,10,11,3,4,11,3,11,12,2,3,12,2,12,13,1,2,13,1,13,14,1,14,15,0,1,15,16,17,0,16,0,15],"vertices":[-5.7,-9.14,-5.7,-3.34,-5.7,2.5,-5.7,7.35,-5.7,12.3,-5.7,16.91,-5.7,21.91,-5.7,26.89,5.3,26.89,5.3,22,5.3,16.87,5.3,12.3,5.3,7.35,5.3,2.17,5.3,-3.38,5.3,-8.9,5.3,-14.11,-5.7,-14.11],"hull":18,"edges":[14,16,32,34,14,12,16,18,12,18,12,10,18,20,10,20,10,8,20,22,8,22,8,6,22,24,6,24,6,4,24,26,4,26,4,2,26,28,2,28,2,0,0,34,28,30,30,32,0,30],"width":11,"height":41}},"Coin2":{"Coin":{"x":0.14,"y":0.57,"width":42,"height":41}},"Coin3":{"Coin":{"x":0.14,"y":0.57,"width":42,"height":41}},"Coin4":{"Coin1":{"type":"mesh","uvs":[0,0.8789,0,0.73724,0,0.5948,0,0.47656,0,0.35597,0,0.24331,0,0.12155,0,0,1,0,1,0.11921,1,0.24448,1,0.35597,1,0.47656,1,0.60299,1,0.73841,1,0.87305,1,1,0,1],"triangles":[7,8,9,6,7,9,10,5,6,10,6,9,4,5,10,4,10,11,3,4,11,3,11,12,2,3,12,2,12,13,1,2,13,1,13,14,1,14,15,0,1,15,16,17,0,16,0,15],"vertices":[-5.7,-9.14,-5.7,-3.34,-5.7,2.5,-5.7,7.35,-5.7,12.3,-5.7,16.91,-5.7,21.91,-5.7,26.89,5.3,26.89,5.3,22,5.3,16.87,5.3,12.3,5.3,7.35,5.3,2.17,5.3,-3.38,5.3,-8.9,5.3,-14.11,-5.7,-14.11],"hull":18,"edges":[14,16,32,34,14,12,16,18,12,18,12,10,18,20,10,20,10,8,20,22,8,22,8,6,22,24,6,24,6,4,24,26,4,26,4,2,26,28,2,28,2,0,0,34,28,30,30,32,0,30],"width":11,"height":41}}}},"animations":{"Coin":{"slots":{"Coin":{"color":[{"time":0,"color":"ffffff00"},{"time":0.0667,"color":"ffffffff","curve":"stepped"},{"time":0.3333,"color":"ffffffff"},{"time":0.5,"color":"ffffff00"}]},"Coin1":{"color":[{"time":0,"color":"ffc30000"},{"time":0.0667,"color":"ffd23fff"},{"time":0.2667,"color":"ffffffff"},{"time":0.3333,"color":"ffc300ff"},{"time":0.5,"color":"ffffff00"}]},"Coin2":{"color":[{"time":0,"color":"ffffff00"},{"time":0.0667,"color":"ffffffff","curve":"stepped"},{"time":0.3333,"color":"ffffffff"},{"time":0.5,"color":"ffffff00"}]},"Coin3":{"color":[{"time":0,"color":"ffffff00"},{"time":0.0667,"color":"ffffff3b"},{"time":0.2667,"color":"ffffff15"},{"time":0.3333,"color":"ffffff47"},{"time":0.5,"color":"ffffff00"}]},"Coin4":{"color":[{"time":0,"color":"ffc30000"},{"time":0.0667,"color":"ffd23f11"},{"time":0.2667,"color":"ffffff47"},{"time":0.3333,"color":"ffc30000"},{"time":0.5,"color":"ffffff00"}]}},"bones":{"root":{"rotate":[{"time":0,"angle":0,"curve":"stepped"},{"time":0.6667,"angle":0}],"translate":[{"time":0,"x":0,"y":0,"curve":"stepped"},{"time":0.6667,"x":0,"y":0}],"scale":[{"time":0,"x":1,"y":1,"curve":"stepped"},{"time":0.6667,"x":1,"y":1}],"shear":[{"time":0,"x":0,"y":0,"curve":"stepped"},{"time":0.6667,"x":0,"y":0}]},"Coin":{"rotate":[{"time":0,"angle":0,"curve":"stepped"},{"time":0.6667,"angle":0}],"translate":[{"time":0,"x":0,"y":0,"curve":[0.25,0,0.75,1]},{"time":0.0667,"x":0,"y":30.73,"curve":[0.25,0,0.75,1]},{"time":0.1333,"x":0,"y":6.54,"curve":[0.25,0,0.75,1]},{"time":0.2333,"x":0,"y":14.93,"curve":[0.25,0,0.75,1]},{"time":0.3333,"x":0,"y":10.01,"curve":[0.25,0,0.75,1]},{"time":0.4333,"x":0,"y":12.85,"curve":[0.25,0,0.75,1]},{"time":0.5333,"x":0,"y":11.1,"curve":"stepped"},{"time":0.6667,"x":0,"y":11.1}],"scale":[{"time":0,"x":1,"y":1,"curve":"stepped"},{"time":0.6667,"x":1,"y":1}],"shear":[{"time":0,"x":0,"y":0,"curve":"stepped"},{"time":0.6667,"x":0,"y":0}]},"Coin2":{"rotate":[{"time":0,"angle":0,"curve":"stepped"},{"time":0.3333,"angle":0,"curve":"stepped"},{"time":0.6667,"angle":0}],"translate":[{"time":0,"x":0,"y":0},{"time":0.1667,"x":-1.88,"y":0,"curve":"stepped"},{"time":0.2,"x":2.65,"y":0},{"time":0.3333,"x":0,"y":0},{"time":0.5,"x":-1.88,"y":0,"curve":"stepped"},{"time":0.5333,"x":2.65,"y":0},{"time":0.6667,"x":0,"y":0}],"scale":[{"time":0,"x":1,"y":1},{"time":0.1,"x":0.504,"y":1},{"time":0.1667,"x":0.01,"y":0.946,"curve":"stepped"},{"time":0.2,"x":0.01,"y":0.946},{"time":0.3333,"x":1,"y":1},{"time":0.4333,"x":0.504,"y":1},{"time":0.5,"x":0.01,"y":0.946,"curve":"stepped"},{"time":0.5333,"x":0.01,"y":0.946},{"time":0.6667,"x":1,"y":1}],"shear":[{"time":0,"x":0,"y":0,"curve":"stepped"},{"time":0.3333,"x":0,"y":0,"curve":"stepped"},{"time":0.6667,"x":0,"y":0}]},"Coin3":{"rotate":[{"time":0,"angle":0,"curve":"stepped"},{"time":0.3333,"angle":0,"curve":"stepped"},{"time":0.6667,"angle":0}],"translate":[{"time":0,"x":0.66,"y":0,"curve":"stepped"},{"time":0.0333,"x":4.9,"y":0},{"time":0.1,"x":4.39,"y":0},{"time":0.1667,"x":2.76,"y":0,"curve":"stepped"},{"time":0.2,"x":-2.14,"y":0},{"time":0.2667,"x":-3.16,"y":0},{"time":0.3,"x":-5.12,"y":0},{"time":0.3333,"x":0.66,"y":0,"curve":"stepped"},{"time":0.3667,"x":3.69,"y":0},{"time":0.4333,"x":4.39,"y":0},{"time":0.5,"x":2.76,"y":0,"curve":"stepped"},{"time":0.5333,"x":-2.14,"y":0},{"time":0.6,"x":-3.16,"y":0},{"time":0.6333,"x":-5.12,"y":0},{"time":0.6667,"x":0.66,"y":0}],"scale":[{"time":0,"x":1,"y":1},{"time":0.1,"x":0.495,"y":1},{"time":0.1667,"x":0.01,"y":0.952,"curve":"stepped"},{"time":0.2,"x":0.01,"y":0.952},{"time":0.2667,"x":0.495,"y":1},{"time":0.3,"x":0.734,"y":1},{"time":0.3333,"x":1,"y":1},{"time":0.4333,"x":0.495,"y":1},{"time":0.5,"x":0.01,"y":0.952,"curve":"stepped"},{"time":0.5333,"x":0.01,"y":0.952},{"time":0.6,"x":0.495,"y":1},{"time":0.6667,"x":1,"y":1}],"shear":[{"time":0,"x":0,"y":0,"curve":"stepped"},{"time":0.3333,"x":0,"y":0,"curve":"stepped"},{"time":0.6667,"x":0,"y":0}]},"Coin1":{"rotate":[{"time":0,"angle":0,"curve":"stepped"},{"time":0.3333,"angle":0,"curve":"stepped"},{"time":0.6667,"angle":0}],"translate":[{"time":0,"x":0,"y":0.53},{"time":0.1,"x":3.04,"y":0.53},{"time":0.1667,"x":0.15,"y":0.53},{"time":0.2667,"x":-1.51,"y":0.53},{"time":0.3333,"x":0,"y":0.53},{"time":0.4333,"x":3.04,"y":0.53},{"time":0.5,"x":0.15,"y":0.53},{"time":0.6,"x":-1.51,"y":0.53},{"time":0.6667,"x":0,"y":0.53}],"scale":[{"time":0,"x":1,"y":1},{"time":0.1667,"x":0.646,"y":1},{"time":0.3333,"x":1,"y":1},{"time":0.5,"x":0.646,"y":1},{"time":0.6667,"x":1,"y":1}]}},"deform":{"default":{"Coin1":{"Coin1":[{"time":0},{"time":0.0333,"offset":18,"vertices":[7.70335,0.06817,14.83092,0.03297,17.66343,-0.43343,19.46527,0.22437,19.17161,-0.08803,16.02981,-1.3662,9.57512,-0.11883]},{"time":0.1,"offset":18,"vertices":[3.52393,-0.144,7.07222,-0.55999,8.66167,-0.35199,9.51713,-0.088,9.30325,-0.44,8.02006,-0.176,4.59814,0.616]},{"time":0.1333,"offset":18,"vertices":[0.85546,-0.1056,3.13011,-0.08797,4.11767,-0.51677,4.58263,-0.03519,3.72688,-0.17598,3.16895,-0.28637,2.18529,0.13843,-0.83718,0.20001]},{"time":0.1667},{"time":0.2333,"vertices":[-1.3122,-0.00002,-2.57972,-0.00002,-3.32805,-0.00002,-3.50395,-0.00001,-2.95698,-0.00002,-2.32963,-0.00002,-0.63353,-0.00001,0.55151,0,0,0,0,0,0,0,0,0,0,0,0,0,0,0,0,0,0,0,0.32663]},{"time":0.2667,"vertices":[-5.29385,-0.00002,-9.23722,-0.00001,-10.78913,-0.00001,-10.39961,-0.00001,-10.18283,-0.00001,-8.56801,-0.00002,-5.83214]},{"time":0.3,"vertices":[-8.00873,-0.00004,-13.51045,-0.00004,-15.88954,-0.00003,-15.87889,-0.00003,-15.02549,-0.00004,-12.7599,-0.00006,-9.07617]},{"time":0.3333},{"time":0.3667,"offset":18,"vertices":[6.54559,-0.09791,12.51884,-0.32451,15.19329,-0.51371,15.98041,-0.05281,15.18511,-0.26402,13.37876,-0.7711,9.38814,0.49058]},{"time":0.4333,"offset":18,"vertices":[3.52393,-0.144,7.07222,-0.55999,8.66167,-0.35199,9.51713,-0.088,9.30325,-0.44,8.02006,-0.176,4.59814,0.616]},{"time":0.4667,"offset":18,"vertices":[0.85546,-0.1056,3.13011,-0.08797,4.11767,-0.51677,4.58263,-0.03519,3.72688,-0.17598,3.16895,-0.28637,2.18529,0.13843,-0.83718,0.20001]},{"time":0.5},{"time":0.5667,"vertices":[-1.3122,-0.00002,-2.57972,-0.00002,-3.32805,-0.00002,-3.50395,-0.00001,-2.95698,-0.00002,-2.32963,-0.00002,-0.63353,-0.00001,0.55151,0,0,0,0,0,0,0,0,0,0,0,0,0,0,0,0,0,0,0,0.32663]},{"time":0.6,"vertices":[-5.29385,-0.00002,-9.23722,-0.00001,-10.78913,-0.00001,-10.39961,-0.00001,-10.18283,-0.00001,-8.56801,-0.00002,-5.83214]},{"time":0.6333,"vertices":[-8.00873,-0.00004,-13.51045,-0.00004,-15.88954,-0.00003,-15.87889,-0.00003,-15.02549,-0.00004,-12.7599,-0.00006,-9.07617]},{"time":0.6667}]},"Coin4":{"Coin1":[{"time":0},{"time":0.0333,"offset":18,"vertices":[6.54559,-0.09791,12.51884,-0.32451,15.19329,-0.51371,15.98041,-0.05281,15.18511,-0.26402,13.37876,-0.7711,9.38814,0.49058]},{"time":0.1,"offset":18,"vertices":[3.52393,-0.144,7.07222,-0.55999,8.66167,-0.35199,9.51713,-0.088,9.30325,-0.44,8.02006,-0.176,4.59814,0.616]},{"time":0.1333,"offset":18,"vertices":[0.85546,-0.1056,3.13011,-0.08797,4.11767,-0.51677,4.58263,-0.03519,3.72688,-0.17598,3.16895,-0.28637,2.18529,0.13843,-0.83718,0.20001]},{"time":0.1667},{"time":0.2333,"vertices":[-1.3122,-0.00002,-2.57972,-0.00002,-3.32805,-0.00002,-3.50395,-0.00001,-2.95698,-0.00002,-2.32963,-0.00002,-0.63353,-0.00001,0.55151,0,0,0,0,0,0,0,0,0,0,0,0,0,0,0,0,0,0,0,0.32663]},{"time":0.2667,"vertices":[-5.29385,-0.00002,-9.23722,-0.00001,-10.78913,-0.00001,-10.39961,-0.00001,-10.18283,-0.00001,-8.56801,-0.00002,-5.83214]},{"time":0.3,"vertices":[-8.00873,-0.00004,-13.51045,-0.00004,-15.88954,-0.00003,-15.87889,-0.00003,-15.02549,-0.00004,-12.7599,-0.00006,-9.07617]},{"time":0.3333},{"time":0.3667,"offset":18,"vertices":[6.54559,-0.09791,12.51884,-0.32451,15.19329,-0.51371,15.98041,-0.05281,15.18511,-0.26402,13.37876,-0.7711,9.38814,0.49058]},{"time":0.4333,"offset":18,"vertices":[3.52393,-0.144,7.07222,-0.55999,8.66167,-0.35199,9.51713,-0.088,9.30325,-0.44,8.02006,-0.176,4.59814,0.616]},{"time":0.4667,"offset":18,"vertices":[0.85546,-0.1056,3.13011,-0.08797,4.11767,-0.51677,4.58263,-0.03519,3.72688,-0.17598,3.16895,-0.28637,2.18529,0.13843,-0.83718,0.20001]},{"time":0.5},{"time":0.5667,"vertices":[-1.3122,-0.00002,-2.57972,-0.00002,-3.32805,-0.00002,-3.50395,-0.00001,-2.95698,-0.00002,-2.32963,-0.00002,-0.63353,-0.00001,0.55151,0,0,0,0,0,0,0,0,0,0,0,0,0,0,0,0,0,0,0,0.32663]},{"time":0.6,"vertices":[-5.29385,-0.00002,-9.23722,-0.00001,-10.78913,-0.00001,-10.39961,-0.00001,-10.18283,-0.00001,-8.56801,-0.00002,-5.83214]},{"time":0.6333,"vertices":[-8.00873,-0.00004,-13.51045,-0.00004,-15.88954,-0.00003,-15.87889,-0.00003,-15.02549,-0.00004,-12.7599,-0.00006,-9.07617]},{"time":0.6667,"vertices":[-10.10186,-0.00005,-16.08721,-0.00006,-18.44912,-0.00006,-18.35423,-0.00005,-17.6049,-0.00006,-15.70514,-0.00007,-11.19325]}]}}}},"Zhuan":{"slots":{"Coin1":{"color":[{"time":0,"color":"ffc300ff"},{"time":0.2667,"color":"ffffffff"},{"time":0.5,"color":"ffc300ff"}]},"Coin3":{"attachment":[{"time":0,"name":null}]},"Coin4":{"color":[{"time":0,"color":"ffc300ff"},{"time":0.2667,"color":"ffffffff"},{"time":0.5,"color":"ffc300ff"}],"attachment":[{"time":0,"name":null}]}},"bones":{"root":{"rotate":[{"time":0,"angle":0,"curve":"stepped"},{"time":0.5,"angle":0}],"translate":[{"time":0,"x":0,"y":0,"curve":"stepped"},{"time":0.5,"x":0,"y":0}],"scale":[{"time":0,"x":1,"y":1,"curve":"stepped"},{"time":0.5,"x":1,"y":1}],"shear":[{"time":0,"x":0,"y":0,"curve":"stepped"},{"time":0.5,"x":0,"y":0}]},"Coin":{"rotate":[{"time":0,"angle":0,"curve":"stepped"},{"time":0.5,"angle":0}],"translate":[{"time":0,"x":0,"y":0,"curve":"stepped"},{"time":0.5,"x":0,"y":0}],"scale":[{"time":0,"x":1,"y":1,"curve":"stepped"},{"time":0.5,"x":1,"y":1}],"shear":[{"time":0,"x":0,"y":0,"curve":"stepped"},{"time":0.5,"x":0,"y":0}]},"Coin2":{"rotate":[{"time":0,"angle":0,"curve":"stepped"},{"time":0.5,"angle":0}],"translate":[{"time":0,"x":0,"y":0},{"time":0.2667,"x":-1.88,"y":0,"curve":"stepped"},{"time":0.3,"x":2.65,"y":0},{"time":0.5,"x":0,"y":0}],"scale":[{"time":0,"x":1,"y":1},{"time":0.1333,"x":0.504,"y":1},{"time":0.2667,"x":0.01,"y":0.946,"curve":"stepped"},{"time":0.3,"x":0.01,"y":0.946},{"time":0.5,"x":1,"y":1}],"shear":[{"time":0,"x":0,"y":0,"curve":"stepped"},{"time":0.5,"x":0,"y":0}]},"Coin3":{"rotate":[{"time":0,"angle":0,"curve":"stepped"},{"time":0.5,"angle":0}],"translate":[{"time":0,"x":0.66,"y":0,"curve":"stepped"},{"time":0.0333,"x":3.69,"y":0},{"time":0.0667,"x":4.9,"y":0},{"time":0.1333,"x":4.39,"y":0},{"time":0.2667,"x":2.76,"y":0,"curve":"stepped"},{"time":0.3,"x":-2.14,"y":0},{"time":0.4,"x":-3.16,"y":0},{"time":0.4333,"x":-5.12,"y":0},{"time":0.4667,"x":-5.25,"y":0},{"time":0.5,"x":0.66,"y":0}],"scale":[{"time":0,"x":1,"y":1},{"time":0.1333,"x":0.495,"y":1},{"time":0.2667,"x":0.01,"y":0.952,"curve":"stepped"},{"time":0.3,"x":0.01,"y":0.952},{"time":0.4,"x":0.495,"y":1},{"time":0.4667,"x":0.734,"y":1},{"time":0.5,"x":1,"y":1}],"shear":[{"time":0,"x":0,"y":0,"curve":"stepped"},{"time":0.5,"x":0,"y":0}]},"Coin1":{"rotate":[{"time":0,"angle":0,"curve":"stepped"},{"time":0.5,"angle":0}],"translate":[{"time":0,"x":0,"y":0.53},{"time":0.1333,"x":3.04,"y":0.53},{"time":0.2667,"x":0.15,"y":0.53},{"time":0.4,"x":-1.51,"y":0.53},{"time":0.5,"x":0,"y":0.53}],"scale":[{"time":0,"x":1,"y":1},{"time":0.2667,"x":0.646,"y":1},{"time":0.5,"x":1,"y":1}]}},"deform":{"default":{"Coin1":{"Coin1":[{"time":0},{"time":0.0333,"offset":18,"vertices":[7.70335,0.06817,14.83092,0.03297,17.66343,-0.43343,19.46527,0.22437,19.17161,-0.08803,16.02981,-1.3662,9.57512,-0.11883]},{"time":0.0667,"offset":18,"vertices":[6.54559,-0.09791,12.51884,-0.32451,15.19329,-0.51371,15.98041,-0.05281,15.18511,-0.26402,13.37876,-0.7711,9.38814,0.49058]},{"time":0.1333,"offset":18,"vertices":[3.52393,-0.144,7.07222,-0.55999,8.66167,-0.35199,9.51713,-0.088,9.30325,-0.44,8.02006,-0.176,4.59814,0.616]},{"time":0.2,"offset":18,"vertices":[0.85546,-0.1056,3.13011,-0.08797,4.11767,-0.51677,4.58263,-0.03519,3.72688,-0.17598,3.16895,-0.28637,2.18529,0.13843,-0.83718,0.20001]},{"time":0.2667},{"time":0.3333,"vertices":[-1.3122,-0.00002,-2.57972,-0.00002,-3.32805,-0.00002,-3.50395,-0.00001,-2.95698,-0.00002,-2.32963,-0.00002,-0.63353,-0.00001,0.55151,0,0,0,0,0,0,0,0,0,0,0,0,0,0,0,0,0,0,0,0.32663]},{"time":0.4,"vertices":[-5.29385,-0.00002,-9.23722,-0.00001,-10.78913,-0.00001,-10.39961,-0.00001,-10.18283,-0.00001,-8.56801,-0.00002,-5.83214]},{"time":0.4333,"vertices":[-8.00873,-0.00004,-13.51045,-0.00004,-15.88954,-0.00003,-15.87889,-0.00003,-15.02549,-0.00004,-12.7599,-0.00006,-9.07617]},{"time":0.4667,"vertices":[-10.10186,-0.00005,-16.08721,-0.00006,-18.44912,-0.00006,-18.35423,-0.00005,-17.6049,-0.00006,-15.70514,-0.00007,-11.19325]},{"time":0.5}]},"Coin4":{"Coin1":[{"time":0},{"time":0.0333,"offset":18,"vertices":[7.70335,0.06817,14.83092,0.03297,17.66343,-0.43343,19.46527,0.22437,19.17161,-0.08803,16.02981,-1.3662,9.57512,-0.11883]},{"time":0.0667,"offset":18,"vertices":[6.54559,-0.09791,12.51884,-0.32451,15.19329,-0.51371,15.98041,-0.05281,15.18511,-0.26402,13.37876,-0.7711,9.38814,0.49058]},{"time":0.1333,"offset":18,"vertices":[3.52393,-0.144,7.07222,-0.55999,8.66167,-0.35199,9.51713,-0.088,9.30325,-0.44,8.02006,-0.176,4.59814,0.616]},{"time":0.2,"offset":18,"vertices":[0.85546,-0.1056,3.13011,-0.08797,4.11767,-0.51677,4.58263,-0.03519,3.72688,-0.17598,3.16895,-0.28637,2.18529,0.13843,-0.83718,0.20001]},{"time":0.2667},{"time":0.3333,"vertices":[-1.3122,-0.00002,-2.57972,-0.00002,-3.32805,-0.00002,-3.50395,-0.00001,-2.95698,-0.00002,-2.32963,-0.00002,-0.63353,-0.00001,0.55151,0,0,0,0,0,0,0,0,0,0,0,0,0,0,0,0,0,0,0,0.32663]},{"time":0.4,"vertices":[-5.29385,-0.00002,-9.23722,-0.00001,-10.78913,-0.00001,-10.39961,-0.00001,-10.18283,-0.00001,-8.56801,-0.00002,-5.83214]},{"time":0.4333,"vertices":[-8.00873,-0.00004,-13.51045,-0.00004,-15.88954,-0.00003,-15.87889,-0.00003,-15.02549,-0.00004,-12.7599,-0.00006,-9.07617]},{"time":0.4667,"vertices":[-10.10186,-0.00005,-16.08721,-0.00006,-18.44912,-0.00006,-18.35423,-0.00005,-17.6049,-0.00006,-15.70514,-0.00007,-11.19325]},{"time":0.5}]}}}}}},"_atlasText":"\nPlayer_Coin.png\nsize: 64,64\nformat: RGBA8888\nfilter: Linear,Linear\nrepeat: none\nCoin\n  rotate: false\n  xy: 2, 15\n  size: 42, 41\n  orig: 42, 41\n  offset: 0, 0\n  index: -1\nCoin1\n  rotate: true\n  xy: 2, 2\n  size: 11, 41\n  orig: 11, 41\n  offset: 0, 0\n  index: -1\n","textures":[{"__uuid__":"521xOKzydA8Ja4ZHD2Hqj/"}],"textureNames":["Player_Coin.png"]}